{
    "uuid": [
        {
            "value": "b83a73fd-7323-4bb4-a55c-3735b1e6643f"
        }
    ],
    "langcode": [
        {
            "value": "en"
        }
    ],
    "shortcut_set": [
        {
            "target_id": "default",
            "target_type": "shortcut_set",
            "target_uuid": "27fda146-a475-493b-8e0c-2e1d88b97aae"
        }
    ],
    "title": [
        {
            "value": "All content"
        }
    ],
    "weight": [
        {
            "value": -19
        }
    ],
    "link": [
        {
            "uri": "internal:\/admin\/content",
            "title": null,
            "options": []
        }
    ],
    "default_langcode": [
        {
            "value": true
        }
    ]
}